[
    {
        "Название": "Незнайка на Луне",
        "Ссылка": "https://www.labirint.ru/books/552591/",
        "Осталось": "0",
        "На руках": "1"
    },
    {
        "Название": "Ночь нежна. Давай поженимся. Немного солнца в холодной воде",
        "Ссылка": "https://fantlab.ru/edition62073",
        "Осталось": "0",
        "На руках": "1"
    },
    {
        "Название": "Роковой выигрыш",
        "Ссылка": "https://www.ozon.ru/product/rokovoy-vyigrysh-averchenko-arkadiy-timofeevich-407179150/?sh=vXhPjy9y0Q",
        "Осталось": "0",
        "На руках": "1"
    },
    {
        "Название": "Осознанность. Как обрести гармонию в нашем безумном мире",
        "Ссылка": "https://www.labirint.ru/books/445413/",
        "Осталось": "1",
        "На руках": "1"
    },
    {
        "Название": "Над пропастью во ржи",
        "Ссылка": "https://www.labirint.ru/books/743181/",
        "Осталось": "1",
        "На руках": "1"
    },
    {
        "Название": "Татьяна Мужицкая: Мне все льзя. О том, как найти свое призвание и самого себя",
        "Ссылка": "https://www.labirint.ru/books/725222/",
        "Осталось": "0",
        "На руках": "1"
    },
    {
        "Название": "Один день Ивана Денисовича",
        "Ссылка": "https://www.labirint.ru/books/716468/",
        "Осталось": "0",
        "На руках": "1"
    },
    {
        "Название": "Роман с самим собой. Как уравновесить внутренние ян и инь и не отвлекаться на всякую хрень",
        "Ссылка": "https://www.labirint.ru/books/782037/",
        "Осталось": "0",
        "На руках": "2"
    },
    {
        "Название": "Хочу и буду. Дополненное издание. 6 правил счастливой жизни или метод Лабковского в действии",
        "Ссылка": "https://www.labirint.ru/books/804626/",
        "Осталось": "1",
        "На руках": "3"
    },
    {
        "Название": "Мы",
        "Ссылка": "https://www.labirint.ru/books/786431/",
        "Осталось": "1",
        "На руках": "2"
    },
    {
        "Название": "Башня ласточки",
        "Ссылка": "https://www.labirint.ru/books/391698/",
        "Осталось": "0",
        "На руках": "1"
    },
    {
        "Название": "Повелитель мух",
        "Ссылка": "https://www.labirint.ru/books/420218/",
        "Осталось": "0",
        "На руках": "1"
    },
    {
        "Название": "Геральт: Последнее желание. Меч Предназначения. Кровь эльфов. Час Презрения",
        "Ссылка": "https://www.labirint.ru/books/379414/",
        "Осталось": "0",
        "На руках": "1"
    },
    {
        "Название": "Имя розы",
        "Ссылка": "https://www.labirint.ru/books/303783/",
        "Осталось": "0",
        "На руках": "1"
    },
    {
        "Название": "Зулейха открывает глаза",
        "Ссылка": "https://www.labirint.ru/books/481894/",
        "Осталось": "0",
        "На руках": "1"
    },
    {
        "Название": "Кысь",
        "Ссылка": "https://www.labirint.ru/books/489247/",
        "Осталось": "1",
        "На руках": "1"
    },
    {
        "Название": "Куджо",
        "Ссылка": "https://www.labirint.ru/books/516749/",
        "Осталось": "0",
        "На руках": "2"
    },
    {
        "Название": "Авиатор",
        "Ссылка": "https://www.labirint.ru/books/526225/",
        "Осталось": "0",
        "На руках": "3"
    },
    {
        "Название": "День опричника",
        "Ссылка": "https://www.labirint.ru/books/577034/",
        "Осталось": "1",
        "На руках": "1"
    },
    {
        "Название": "Похождения бравого солдата Швейка",
        "Ссылка": "https://www.labirint.ru/books/640171/",
        "Осталось": "1",
        "На руках": "1"
    },
    {
        "Название": "S.N.U.F.F.",
        "Ссылка": "https://www.labirint.ru/books/641226/",
        "Осталось": "0",
        "На руках": "1"
    },
    {
        "Название": "Прокляты и убиты",
        "Ссылка": "https://www.labirint.ru/books/644078/",
        "Осталось": "0",
        "На руках": "1"
    },
    {
        "Название": "Старик и море. Острова и море",
        "Ссылка": "https://www.labirint.ru/books/761351/",
        "Осталось": "1",
        "На руках": "2"
    },
    {
        "Название": "Понедельник начинается в субботу",
        "Ссылка": "https://www.labirint.ru/books/721079/",
        "Осталось": "1",
        "На руках": "1"
    },
    {
        "Название": "Стругацкий, Стругацкий: Обитаемый остров",
        "Ссылка": "https://www.labirint.ru/books/726692/",
        "Осталось": "0",
        "На руках": "1"
    },
    {
        "Название": "Лавр (иллюстрации Леонида Губского)",
        "Ссылка": "https://www.labirint.ru/books/741618/",
        "Осталось": "1",
        "На руках": "1"
    },
    {
        "Название": "Владимир Войнович: Москва 2042",
        "Ссылка": "https://www.labirint.ru/books/794975/",
        "Осталось": "0",
        "На руках": "3"
    },
    {
        "Название": "Остромов, или Ученик чародея",
        "Ссылка": "https://www.labirint.ru/books/775397/",
        "Осталось": "1",
        "На руках": "1"
    },
    {
        "Название": "О дивный новый мир",
        "Ссылка": "https://www.labirint.ru/books/763301/",
        "Осталось": "1",
        "На руках": "2"
    },
    {
        "Название": "Истребитель",
        "Ссылка": "https://www.labirint.ru/books/794491/",
        "Осталось": "1",
        "На руках": "1"
    },
    {
        "Название": "На западном фронте без перемен",
        "Ссылка": "https://www.labirint.ru/books/813041/",
        "Осталось": "0",
        "На руках": "2"
    },
    {
        "Название": "Лолита",
        "Ссылка": "https://www.labirint.ru/books/811681/",
        "Осталось": "1",
        "На руках": "2"
    },
    {
        "Название": "Стивен Кинг: Худеющий",
        "Ссылка": "https://www.labirint.ru/books/868404/\r\n",
        "Осталось": "1",
        "На руках": "1"
    },
    {
        "Название": "О свободе и рабстве человека. Опыт персоналистической философии",
        "Ссылка": "https://www.labirint.ru/books/822421/",
        "Осталось": "1",
        "На руках": "1"
    },
    {
        "Название": "Одесские рассказы",
        "Ссылка": "https://www.labirint.ru/books/406050/",
        "Осталось": "0",
        "На руках": "1"
    },
    {
        "Название": "Эрос и мораль",
        "Ссылка": "https://www.labirint.ru/books/637729/",
        "Осталось": "0",
        "На руках": "1"
    },
    {
        "Название": "Как работает пропаганда",
        "Ссылка": "https://www.labirint.ru/books/665572/",
        "Осталось": "0",
        "На руках": "1"
    },
    {
        "Название": "Лето в пионерском галстуке",
        "Ссылка": "https://www.labirint.ru/books/848303/",
        "Осталось": "0",
        "На руках": "1"
    },
    {
        "Название": "Золотой жук и другие мистические истории",
        "Ссылка": "https://www.labirint.ru/books/487662/",
        "Осталось": "1",
        "На руках": "1"
    },
    {
        "Название": "Торговцы во времени",
        "Ссылка": "https://www.labirint.ru/books/577832/",
        "Осталось": "1",
        "На руках": "1"
    },
    {
        "Название": "Котлован",
        "Ссылка": "https://www.labirint.ru/books/582911/",
        "Осталось": "1",
        "На руках": "1"
    },
    {
        "Название": "НИ СЫ. Будь уверен в своих силах и не позволяй сомнениям мешать тебе двигаться вперед ",
        "Ссылка": "https://www.labirint.ru/books/625830/",
        "Осталось": "0",
        "На руках": "1"
    },
    {
        "Название": "Замок",
        "Ссылка": "https://www.labirint.ru/books/786918/",
        "Осталось": "0",
        "На руках": "1"
    },
    {
        "Название": "Бойня",
        "Ссылка": "https://www.labirint.ru/books/810401/",
        "Осталось": "0",
        "На руках": "1"
    },
    {
        "Название": "Раиса Горбачева. Штрихи к портрету",
        "Ссылка": "https://www.ozon.ru/product/raisa-gorbacheva-shtrihi-k-portretu-mamardashvili-nina-bush-barbara-616363980/?asb=Waf4ZzHVg8K",
        "Осталось": "0",
        "На руках": "1"
    }
]